pysilico_server/__init__.py
pysilico_server/__version__.py
pysilico_server/calib/dark_frame/none.fits
pysilico_server/camera_controller/__init__.py
pysilico_server/camera_controller/camera_controller.py
pysilico_server/camera_controller/pysilico_run_camera_controller.py
pysilico_server/camera_controller/runner.py
pysilico_server/conf/pysilico_server.conf
pysilico_server/devices/__init__.py
pysilico_server/devices/abstract_camera.py
pysilico_server/devices/avtCamera.py
pysilico_server/devices/base_simulated_camera.py
pysilico_server/devices/basler_camera.py
pysilico_server/devices/ocam2KCamera.py
pysilico_server/devices/simulated_auxiliary_camera.py
pysilico_server/devices/simulated_camera.py
pysilico_server/process_monitor/__init__.py
pysilico_server/process_monitor/pysilico_run_process_monitor.py
pysilico_server/process_monitor/runner.py
pysilico_server/scripts/__init__.py
pysilico_server/scripts/pysilico_camera_controller.py
pysilico_server/scripts/pysilico_kill_processes.py
pysilico_server/scripts/pysilico_process_monitor.py
pysilico_server/scripts/pysilico_stop.py
pysilico_server/utils/__init__.py
pysilico_server/utils/constants.py
pysilico_server/utils/process_startup_helper.py
pysilico_server/utils/starter_script_creator.py
pysilico_server-0.22.0.dist-info/LICENSE
pysilico_server-0.22.0.dist-info/METADATA
pysilico_server-0.22.0.dist-info/WHEEL
pysilico_server-0.22.0.dist-info/entry_points.txt
pysilico_server-0.22.0.dist-info/top_level.txt
pysilico_server-0.22.0.dist-info/RECORD
