Metadata-Version: 2.1
Name: pysilico-server
Version: 0.22.0
Summary: AVT-Prosilica camera controller with PLICO
Home-page: https://github.com/lbusoni/pysilico_server
Author: Lorenzo Busoni
Author-email: lorenzo.busoni@inaf.it
License: MIT
Keywords: plico,Prosilica,AVT,camera,laboratory,instrumentation control
Classifier: Development Status :: 4 - Beta
Classifier: Operating System :: POSIX :: Linux
Classifier: Programming Language :: Python :: 3
License-File: LICENSE
Requires-Dist: plico >=0.25
Requires-Dist: pysilico >=0.19
Requires-Dist: numpy
Requires-Dist: psutil
Requires-Dist: six
Requires-Dist: rebin
